pypsexec/__init__.py
pypsexec/client.py
pypsexec/exceptions.py
pypsexec/paexec.exe
pypsexec/paexec.py
pypsexec/pipe.py
pypsexec/rpc.py
pypsexec/scmr.py
pypsexec-0.3.0.dist-info/LICENSE
pypsexec-0.3.0.dist-info/METADATA
pypsexec-0.3.0.dist-info/WHEEL
pypsexec-0.3.0.dist-info/top_level.txt
pypsexec-0.3.0.dist-info/RECORD
