Metadata-Version: 2.1
Name: pypsexec
Version: 0.3.0
Summary: Run commands on a remote Windows host using SMB/RPC
Home-page: https://github.com/jborean93/pypsexec
Author: Jordan Borean
Author-email: jborean93@gmail.com
License: MIT
Keywords: windows psexec paexec remote python
Platform: UNKNOWN
Classifier: Development Status :: 4 - Beta
Classifier: License :: OSI Approved :: MIT License
Classifier: Programming Language :: Python :: 3
Classifier: Programming Language :: Python :: 3.6
Classifier: Programming Language :: Python :: 3.7
Classifier: Programming Language :: Python :: 3.8
Classifier: Programming Language :: Python :: 3.9
Classifier: Programming Language :: Python :: 3.10
Requires-Python: >=3.6
License-File: LICENSE
